funcdesc/__init__.py
funcdesc/desc.py
funcdesc/guard.py
funcdesc/mark.py
funcdesc/parse.py
funcdesc/pydantic.py
funcdesc/types/__init__.py
funcdesc/types/side_effects.py
funcdesc/types/value.py
funcdesc/utils/__init__.py
funcdesc/utils/json.py
funcdesc/utils/misc.py
funcdesc-0.2.1.dist-info/licenses/LICENSE
tests/conftest.py
tests/test_docstring.py
tests/test_funcdesc.py
tests/test_pydantic.py
tests/test_signature.py
tests/test_types.py
funcdesc-0.2.1.dist-info/METADATA
funcdesc-0.2.1.dist-info/WHEEL
funcdesc-0.2.1.dist-info/top_level.txt
funcdesc-0.2.1.dist-info/RECORD
