Metadata-Version: 2.4
Name: funcdesc
Version: 0.2.1
Summary: Establish a general function description protocol, which can realize a comprehensive description of the input, output and side effects of an target function through an Python object. Provide a unified abstraction for parameter checking, interface generation and other functions in applications such as oneFace.
Author-email: Weize Xu <vet.xwz@gmail.com>
License: MIT
Project-URL: Homepage, https://github.com/Nanguage/funcdesc
Project-URL: Repository, https://github.com/Nanguage/funcdesc
Keywords: funcdesc
Classifier: Development Status :: 2 - Pre-Alpha
Classifier: Intended Audience :: Developers
Classifier: License :: OSI Approved :: MIT License
Classifier: Natural Language :: English
Classifier: Programming Language :: Python :: 3
Classifier: Programming Language :: Python :: 3.10
Classifier: Programming Language :: Python :: 3.11
Classifier: Programming Language :: Python :: 3.12
Requires-Python: >=3.10
License-File: LICENSE
Provides-Extra: dev
Requires-Dist: pytest; extra == "dev"
Requires-Dist: pytest-cov; extra == "dev"
Requires-Dist: flake8; extra == "dev"
Requires-Dist: mypy; extra == "dev"
Requires-Dist: pydantic>=2.10.4; extra == "dev"
Requires-Dist: docstring_parser>=0.16; extra == "dev"
Dynamic: license-file
